README.md
setup.py
firestore_operators/__init__.py
firestore_operators.egg-info/PKG-INFO
firestore_operators.egg-info/SOURCES.txt
firestore_operators.egg-info/dependency_links.txt
firestore_operators.egg-info/top_level.txt
firestore_operators/operators/__init__.py
firestore_operators/operators/firestore_operator.py