Metadata-Version: 2.1
Name: firestore-operators
Version: 0.0.4
Summary: Operator to send data to Firestore from Airflow
Home-page: https://github.com/properati/firestore_operator
Author: Cezar Azevedo de Faveri
Author-email: cazevedodefaveri@gmail.com
License: UNKNOWN
Platform: UNKNOWN
Requires-Python: >=3.6
